zipline_crypto-0.1.dist-info/LICENSE
zipline_crypto-0.1.dist-info/top_level.txt
zipline_crypto-0.1.dist-info/WHEEL
zipline_crypto-0.1.dist-info/entry_points.txt
zipline_crypto-0.1.dist-info/RECORD
zipline_crypto-0.1.dist-info/METADATA
zipline/country.py
zipline/currency.py
zipline/api.pyi
zipline/errors.py
zipline/dispatch.py
zipline/protocol.py
zipline/api.py
zipline/_version.py
zipline/_protocol.cpython-310-x86_64-linux-gnu.so
zipline/algorithm.py
zipline/_protocol.pxd
zipline/test_algorithms.py
zipline/zipline_warnings.py
zipline/_protocol.pyx
zipline/__main__.py
zipline/extensions.py
zipline/__init__.py
zipline/utils/preprocess.py
zipline/utils/factory.py
zipline/utils/string_formatting.py
zipline/utils/security_list.py
zipline/utils/sqlite_utils.py
zipline/utils/functional.py
zipline/utils/cli.py
zipline/utils/exploding_object.py
zipline/utils/compat.py
zipline/utils/date_utils.py
zipline/utils/input_validation.py
zipline/utils/classproperty.py
zipline/utils/idbox.py
zipline/utils/data.py
zipline/utils/events.py
zipline/utils/memoize.py
zipline/utils/numpy_utils.py
zipline/utils/api_support.py
zipline/utils/argcheck.py
zipline/utils/sentinel.py
zipline/utils/cache.py
zipline/utils/deprecate.py
zipline/utils/range.py
zipline/utils/final.py
zipline/utils/sharedoc.py
zipline/utils/math_utils.py
zipline/utils/algo_instance.py
zipline/utils/dummy.py
zipline/utils/paths.py
zipline/utils/pandas_utils.py
zipline/utils/context_tricks.py
zipline/utils/formatting.py
zipline/utils/calendar_utils.py
zipline/utils/run_algo.py
zipline/utils/__init__.py
zipline/lib/adjustment.pyx
zipline/lib/labelarray.py
zipline/lib/adjusted_array.py
zipline/lib/rank.cpython-310-x86_64-linux-gnu.so
zipline/lib/_float64window.pyx
zipline/lib/quantiles.py
zipline/lib/_factorize.pyx
zipline/lib/_uint8window.pyx
zipline/lib/adjustment.cpython-310-x86_64-linux-gnu.so
zipline/lib/normalize.py
zipline/lib/_labelwindow.pyx
zipline/lib/rank.pyx
zipline/lib/_int64window.pyx
zipline/lib/_labelwindow.cpython-310-x86_64-linux-gnu.so
zipline/lib/_int64window.cpython-310-x86_64-linux-gnu.so
zipline/lib/_uint8window.cpython-310-x86_64-linux-gnu.so
