Metadata-Version: 2.1
Name: zipline-crypto
Version: 0.1
Summary: A backtester for trading algorithms
Home-page: https://zipline.ml4trading.io
Author: Quantopian Inc
Author-email: pm@ml4trading.io
License: Apache 2.0
Classifier: Development Status :: 4 - Beta
Classifier: License :: OSI Approved :: Apache Software License
Classifier: Natural Language :: English
Classifier: Programming Language :: Python
Classifier: Programming Language :: Python :: 3.9
Classifier: Programming Language :: Python :: 3.10
Classifier: Operating System :: OS Independent
Classifier: Intended Audience :: Science/Research
Classifier: Topic :: Office/Business :: Financial :: Investment
Classifier: Topic :: Scientific/Engineering :: Information Analysis
Classifier: Topic :: System :: Distributed Computing
Requires-Python: >=3.10
License-File: LICENSE
Requires-Dist: alembic (>=0.7.7)
Requires-Dist: bcolz-zipline (>=1.2.5)
Requires-Dist: bottleneck (>=1.0.0)
Requires-Dist: click (>=4.0.0)
Requires-Dist: empyrical-reloaded (>=0.5.7)
Requires-Dist: h5py (>=2.7.1)
Requires-Dist: intervaltree (>=2.1.0)
Requires-Dist: iso3166 (>=2.1.1)
Requires-Dist: iso4217 (>=1.6.20180829)
Requires-Dist: logbook (>=1.0)
Requires-Dist: lru-dict (>=1.1.4)
Requires-Dist: multipledispatch (>=0.6.0)
Requires-Dist: networkx (>=2.0)
Requires-Dist: numexpr (>=2.6.1)
Requires-Dist: numpy (<1.23,>=1.22.0)
Requires-Dist: pandas (<1.6,>=1.5.1)
Requires-Dist: patsy (>=0.4.0)
Requires-Dist: python-dateutil (>=2.4.2)
Requires-Dist: python-interface (>=1.5.3)
Requires-Dist: pytz (>=2018.5)
Requires-Dist: requests (>=2.9.1)
Requires-Dist: scipy (>=0.17.1)
Requires-Dist: six (>=1.10.0)
Requires-Dist: sqlalchemy (>=2.0.0b3)
Requires-Dist: statsmodels (>=0.6.1)
Requires-Dist: ta-lib (<0.4.25,>=0.4.09)
Requires-Dist: tables (>=3.4.3)
Requires-Dist: toolz (>=0.8.2)
Requires-Dist: trading-calendars (>=1.6.1)
Requires-Dist: exchange-calendars (<=3.3)
Provides-Extra: all
Requires-Dist: Cython ; extra == 'all'
Requires-Dist: Sphinx (>=1.3.2) ; extra == 'all'
Requires-Dist: numpydoc (>=0.5.0) ; extra == 'all'
Requires-Dist: sphinx-autobuild (>=0.6.0) ; extra == 'all'
Requires-Dist: pydata-sphinx-theme ; extra == 'all'
Requires-Dist: sphinx-markdown-tables ; extra == 'all'
Requires-Dist: m2r2 ; extra == 'all'
Requires-Dist: flake8 (>=3.9.1) ; extra == 'all'
Requires-Dist: black ; extra == 'all'
Requires-Dist: pre-commit (>=2.12.1) ; extra == 'all'
Requires-Dist: tox ; extra == 'all'
Requires-Dist: pytest (>=7.1.1) ; extra == 'all'
Requires-Dist: pytest-cov (>=3.0.0) ; extra == 'all'
Requires-Dist: pytest-xdist (>=2.5.0) ; extra == 'all'
Requires-Dist: pytest-timeout (>=1.4.2) ; extra == 'all'
Requires-Dist: parameterized (>=0.6.1) ; extra == 'all'
Requires-Dist: mock (>=2.0.0p) ; extra == 'all'
Requires-Dist: testfixtures (>=4.1.2) ; extra == 'all'
Requires-Dist: matplotlib (>=1.5.3) ; extra == 'all'
Requires-Dist: responses (>=0.9.0) ; extra == 'all'
Requires-Dist: pandas (<1.6,>=1.5.1) ; extra == 'all'
Requires-Dist: pandas-datareader (>=0.2.1) ; extra == 'all'
Requires-Dist: click (<8.1.0) ; extra == 'all'
Requires-Dist: coverage ; extra == 'all'
Provides-Extra: dev
Requires-Dist: flake8 (>=3.9.1) ; extra == 'dev'
Requires-Dist: black ; extra == 'dev'
Requires-Dist: pre-commit (>=2.12.1) ; extra == 'dev'
Provides-Extra: docs
Requires-Dist: Cython ; extra == 'docs'
Requires-Dist: Sphinx (>=1.3.2) ; extra == 'docs'
Requires-Dist: numpydoc (>=0.5.0) ; extra == 'docs'
Requires-Dist: sphinx-autobuild (>=0.6.0) ; extra == 'docs'
Requires-Dist: pydata-sphinx-theme ; extra == 'docs'
Requires-Dist: sphinx-markdown-tables ; extra == 'docs'
Requires-Dist: m2r2 ; extra == 'docs'
Provides-Extra: test
Requires-Dist: tox ; extra == 'test'
Requires-Dist: pytest (>=7.1.1) ; extra == 'test'
Requires-Dist: pytest-cov (>=3.0.0) ; extra == 'test'
Requires-Dist: pytest-xdist (>=2.5.0) ; extra == 'test'
Requires-Dist: pytest-timeout (>=1.4.2) ; extra == 'test'
Requires-Dist: parameterized (>=0.6.1) ; extra == 'test'
Requires-Dist: mock (>=2.0.0p) ; extra == 'test'
Requires-Dist: testfixtures (>=4.1.2) ; extra == 'test'
Requires-Dist: flake8 (>=3.9.1) ; extra == 'test'
Requires-Dist: matplotlib (>=1.5.3) ; extra == 'test'
Requires-Dist: responses (>=0.9.0) ; extra == 'test'
Requires-Dist: pandas (<1.6,>=1.5.1) ; extra == 'test'
Requires-Dist: pandas-datareader (>=0.2.1) ; extra == 'test'
Requires-Dist: click (<8.1.0) ; extra == 'test'
Requires-Dist: coverage ; extra == 'test'
